hearvalidator/__init__.py
hearvalidator/validate.py
hearvalidator-2021.0.6.dist-info/LICENSE
hearvalidator-2021.0.6.dist-info/METADATA
hearvalidator-2021.0.6.dist-info/WHEEL
hearvalidator-2021.0.6.dist-info/entry_points.txt
hearvalidator-2021.0.6.dist-info/top_level.txt
hearvalidator-2021.0.6.dist-info/RECORD
