Metadata-Version: 2.1
Name: hearvalidator
Version: 2021.0.6
Summary: Holistic Evaluation of Audio Representations (HEAR) 2021 -- Submission Validator
Home-page: https://github.com/hearbenchmark/hear-validator
Author: HEAR 2021 NeurIPS Competition Committee
Author-email: deep@neuralaudio.ai
License: Apache-2.0
Project-URL: Bug Tracker, https://github.com/hearbenchmark/hear-validator/issues
Project-URL: Source Code, https://github.com/hearbenchmark/hear-validator
Requires-Python: >=3.6, <3.9
License-File: LICENSE
Requires-Dist: tensorflow (>=2.0)
Requires-Dist: torch (>=1.7)
Provides-Extra: dev
Requires-Dist: pre-commit ; extra == 'dev'
Requires-Dist: black ; extra == 'dev'
